animadao/__init__.py
animadao/cli.py
animadao/config.py
animadao/dependency_checker.py
animadao/import_scanner.py
animadao/native.py
animadao/precommit_gate.py
animadao/report_generator.py
animadao/version_checker.py
anima_dao-0.2.0.dist-info/METADATA
anima_dao-0.2.0.dist-info/WHEEL
anima_dao-0.2.0.dist-info/entry_points.txt
anima_dao-0.2.0.dist-info/licenses/LICENSE
anima_dao-0.2.0.dist-info/RECORD
