Metadata-Version: 2.4
Name: anima-dao
Version: 0.2.0
Summary: Confucian-spirited dependency health checker for Python projects using pyproject + uv
Project-URL: Homepage, https://github.com/Absolentia/AnimaDao
Project-URL: Repository, https://github.com/Absolentia/AnimaDao
Project-URL: Issues, https://github.com/Absolentia/AnimaDao/issues
Author-email: Dmitry Kosarevsky <if@kosarevsky.ru>
License-Expression: MIT
License-File: LICENSE
Classifier: License :: OSI Approved :: MIT License
Classifier: Operating System :: OS Independent
Classifier: Programming Language :: Python :: 3
Classifier: Programming Language :: Python :: 3.10
Classifier: Programming Language :: Python :: 3.11
Classifier: Programming Language :: Python :: 3.12
Classifier: Programming Language :: Python :: 3.13
Classifier: Programming Language :: Python :: 3.14
Classifier: Topic :: Software Development :: Build Tools
Requires-Python: >=3.11
Requires-Dist: click>=8.2.1
Requires-Dist: httpx>=0.28.1
Requires-Dist: packaging>=23.2
Requires-Dist: tomli>=2.0.1; python_version < '3.11'
Provides-Extra: dev
Requires-Dist: build>=1.2.1; extra == 'dev'
Requires-Dist: pytest-asyncio>=1.1.0; extra == 'dev'
Requires-Dist: pytest>=8.4.1; extra == 'dev'
Requires-Dist: ruff>=0.12.8; extra == 'dev'
Requires-Dist: twine>=5.0.0; extra == 'dev'
Provides-Extra: native
Requires-Dist: anima-core>=0.1.1; extra == 'native'
